<?xml version="1.0" encoding="UTF-8"?>
<!DOCTYPE mapper PUBLIC "-//mybatis.org//DTD Mapper 3.0//EN" "http://mybatis.org/dtd/mybatis-3-mapper.dtd">
<mapper namespace="com.dragon.flow.mapper.form.IFormDataInfoMapper">

    <!-- 通用查询映射结果 -->
    <resultMap id="BaseResultMap" type="com.dragon.flow.model.form.FormDataInfo">
        <id column="id" property="id" />
        <result column="model_key" property="modelKey" />
        <result column="business_key" property="businessKey" />
        <result column="process_instance_id" property="processInstanceId" />
        <result column="formData" property="formData" />
    </resultMap>

    <!-- 通用查询结果列 -->
    <sql id="Base_Column_List">
        id, model_key, business_key, process_instance_id, formData
    </sql>

</mapper>
